cmp_sdk/__init__.py
cmp_sdk/const.py
cmp_sdk/logger.py
cmp_sdk/method.py
cmp_sdk/models.py
cmp_sdk/parser.py
cmp_sdk/request.py
cmp_sdk-1.0.14.dist-info/METADATA
cmp_sdk-1.0.14.dist-info/WHEEL
cmp_sdk-1.0.14.dist-info/top_level.txt
cmp_sdk-1.0.14.dist-info/RECORD
