Metadata-Version: 2.1
Name: cmp-sdk
Version: 1.0.14
Summary: cmp sdk
Home-page: UNKNOWN
Author: quwan
Author-email: Csjs1-2@example.com
License: MIT
Platform: UNKNOWN
Classifier: Programming Language :: Python :: 3
Classifier: Programming Language :: Python :: 3.7
Requires-Dist: requests
Requires-Dist: python-dateutil
Requires-Dist: bumpversion
